AUTHORS.txt
CHANGELOG.md
LICENSE.txt
MANIFEST.in
README.md
pyproject.toml
setup.json
setup.py
aiida/__init__.py
aiida/settings.py
aiida/backends/__init__.py
aiida/backends/profile.py
aiida/backends/settings.py
aiida/backends/testbase.py
aiida/backends/testimplbase.py
aiida/backends/utils.py
aiida/backends/djsite/__init__.py
aiida/backends/djsite/globalsettings.py
aiida/backends/djsite/manage.py
aiida/backends/djsite/queries.py
aiida/backends/djsite/utils.py
aiida/backends/djsite/db/__init__.py
aiida/backends/djsite/db/models.py
aiida/backends/djsite/db/testbase.py
aiida/backends/djsite/db/migrations/0001_initial.py
aiida/backends/djsite/db/migrations/0002_db_state_change.py
aiida/backends/djsite/db/migrations/0003_add_link_type.py
aiida/backends/djsite/db/migrations/0004_add_daemon_and_uuid_indices.py
aiida/backends/djsite/db/migrations/0005_add_cmtime_indices.py
aiida/backends/djsite/db/migrations/0006_delete_dbpath.py
aiida/backends/djsite/db/migrations/0007_update_linktypes.py
aiida/backends/djsite/db/migrations/0008_code_hidden_to_extra.py
aiida/backends/djsite/db/migrations/0009_base_data_plugin_type_string.py
aiida/backends/djsite/db/migrations/0010_process_type.py
aiida/backends/djsite/db/migrations/0011_delete_kombu_tables.py
aiida/backends/djsite/db/migrations/0012_drop_dblock.py
aiida/backends/djsite/db/migrations/0013_django_1_8.py
aiida/backends/djsite/db/migrations/0014_add_node_uuid_unique_constraint.py
aiida/backends/djsite/db/migrations/0015_invalidating_node_hash.py
aiida/backends/djsite/db/migrations/0016_code_sub_class_of_data.py
aiida/backends/djsite/db/migrations/0017_drop_dbcalcstate.py
aiida/backends/djsite/db/migrations/0018_django_1_11.py
aiida/backends/djsite/db/migrations/0019_migrate_builtin_calculations.py
aiida/backends/djsite/db/migrations/0020_provenance_redesign.py
aiida/backends/djsite/db/migrations/0021_dbgroup_name_to_label_type_to_type_string.py
aiida/backends/djsite/db/migrations/0022_dbgroup_type_string_change_content.py
aiida_core_bot.egg-info/PKG-INFO
aiida_core_bot.egg-info/SOURCES.txt
aiida_core_bot.egg-info/dependency_links.txt
aiida_core_bot.egg-info/entry_points.txt
aiida_core_bot.egg-info/requires.txt
aiida_core_bot.egg-info/top_level.txt
