Metadata-Version: 2.1
Name: aiida-core-bot
Version: 1.0.0b5
Summary: UNKNOWN
Home-page: http://www.aiida.net/
Author: The AiiDA team
Author-email: developers@aiida.net
License: MIT License
Platform: UNKNOWN
Classifier: License :: OSI Approved :: MIT License
Classifier: Operating System :: POSIX :: Linux
Classifier: Operating System :: MacOS :: MacOS X
Classifier: Programming Language :: Python
Classifier: Programming Language :: Python :: 2.7
Classifier: Programming Language :: Python :: 3.5
Classifier: Programming Language :: Python :: 3.6
Classifier: Topic :: Scientific/Engineering
Provides-Extra: ssh_kerberos
Provides-Extra: all
Provides-Extra: docs
Provides-Extra: rest
Provides-Extra: notebook
Provides-Extra: dev_precommit
Provides-Extra: testing
Provides-Extra: atomic_tools
Provides-Extra: bpython
